HtmlTemplateParser/__init__.py
HtmlTemplateParser/attribute_parser.py
HtmlTemplateParser/html_template_parser.py
html_template_parser-1.7.0.dist-info/LICENSE
html_template_parser-1.7.0.dist-info/WHEEL
html_template_parser-1.7.0.dist-info/METADATA
html_template_parser-1.7.0.dist-info/RECORD
