Metadata-Version: 2.1
Name: html-template-parser
Version: 1.7.0
Summary: A parser for HTML templates.
Home-page: https://github.com/Riverside-Healthcare/html-void-elements
License: GPL-3.0-or-later
Author: Christopher Pickering
Author-email: cpickering@rhc.net
Requires-Python: >=3.7,<4.0
Classifier: License :: OSI Approved :: GNU General Public License v3 or later (GPLv3+)
Classifier: Programming Language :: Python :: 3
Classifier: Programming Language :: Python :: 3.7
Classifier: Programming Language :: Python :: 3.8
Classifier: Programming Language :: Python :: 3.9
Classifier: Programming Language :: Python :: 3.10
Classifier: Programming Language :: Python :: 3.11
Project-URL: Repository, https://github.com/Riverside-Healthcare/html-void-elements
